stix_shifter_modules/proofpoint/__init__.py
stix_shifter_modules/proofpoint/entry_point.py
stix_shifter_modules/proofpoint/configuration/config.json
stix_shifter_modules/proofpoint/configuration/dialects.json
stix_shifter_modules/proofpoint/configuration/lang_en.json
stix_shifter_modules/proofpoint/stix_translation/__init__.py
stix_shifter_modules/proofpoint/stix_translation/json_to_stix_translator.py
stix_shifter_modules/proofpoint/stix_translation/query_constructor.py
stix_shifter_modules/proofpoint/stix_translation/query_translator.py
stix_shifter_modules/proofpoint/stix_translation/transformers.py
stix_shifter_modules/proofpoint/stix_translation/json/from_stix_map.json
stix_shifter_modules/proofpoint/stix_translation/json/operators.json
stix_shifter_modules/proofpoint/stix_translation/json/to_stix_map.json
stix_shifter_modules/proofpoint/stix_transmission/__init__.py
stix_shifter_modules/proofpoint/stix_transmission/api_client.py
stix_shifter_modules/proofpoint/stix_transmission/delete_connector.py
stix_shifter_modules/proofpoint/stix_transmission/error_mapper.py
stix_shifter_modules/proofpoint/stix_transmission/ping_connector.py
stix_shifter_modules/proofpoint/stix_transmission/query_connector.py
stix_shifter_modules/proofpoint/stix_transmission/results_connector.py
stix_shifter_modules/proofpoint/stix_transmission/status_connector.py
stix_shifter_modules/proofpoint/tests/__init__.py
stix_shifter_modules/proofpoint/tests/stix_translation/__init__.py
stix_shifter_modules/proofpoint/tests/stix_translation/test_proofpoint_json_to_stix.py
stix_shifter_modules/proofpoint/tests/stix_translation/test_proofpoint_stix_to_query.py
stix_shifter_modules_proofpoint-8.0.2.dist-info/licenses/AUTHORS.md
stix_shifter_modules_proofpoint-8.0.2.dist-info/licenses/LICENSE.md
stix_shifter_modules_proofpoint-8.0.2.dist-info/licenses/NOTICE
stix_shifter_modules_proofpoint-8.0.2.dist-info/METADATA
stix_shifter_modules_proofpoint-8.0.2.dist-info/WHEEL
stix_shifter_modules_proofpoint-8.0.2.dist-info/top_level.txt
stix_shifter_modules_proofpoint-8.0.2.dist-info/RECORD
